ibmaceflowtester/__init__.py
ibmaceflowtester/classes/__init__.py
ibmaceflowtester/classes/httptest.py
ibmaceflowtester/classes/mqtest.py
ibmaceflowtester/main/__init__.py
ibmaceflowtester/main/runallyaml.py
ibmaceflowtester/util/__init__.py
ibmaceflowtester/util/diff.py
ibmaceflowtester/util/io.py
ibmaceflowtester/util/log.py
ibmaceflowtester-1.2.4.dist-info/METADATA
ibmaceflowtester-1.2.4.dist-info/WHEEL
ibmaceflowtester-1.2.4.dist-info/top_level.txt
ibmaceflowtester-1.2.4.dist-info/RECORD
