Metadata-Version: 2.1
Name: ibmaceflowtester
Version: 1.2.4
Summary: Package to perform tests for IBM ACE interfaces
Home-page: https://github.com/JLanda91/ibm-ace-flow-tester
Author: Jasper Landa
Author-email: jasperlanda91@gmail.com
License: UNKNOWN
Platform: UNKNOWN
Classifier: Programming Language :: Python :: 3
Classifier: License :: OSI Approved :: MIT License
Classifier: Operating System :: OS Independent
Requires-Python: >=3.6
Requires-Dist: PyYAML
Requires-Dist: requests
